README.txt
setup.cfg
setup.py
Products/__init__.py
Products.mediaObject.egg-info/PKG-INFO
Products.mediaObject.egg-info/SOURCES.txt
Products.mediaObject.egg-info/dependency_links.txt
Products.mediaObject.egg-info/entry_points.txt
Products.mediaObject.egg-info/namespace_packages.txt
Products.mediaObject.egg-info/not-zip-safe
Products.mediaObject.egg-info/paster_plugins.txt
Products.mediaObject.egg-info/requires.txt
Products.mediaObject.egg-info/top_level.txt
Products/mediaObject/__init__.py
Products/mediaObject/object.py
Products/mediaObject/tests.py