Metadata-Version: 1.1
Name: Products.mediaObject
Version: 0.1
Summary: Dexterity type that stores information about a collectible object used by museums
Home-page: http://svn.plone.org/svn/collective/
Author: UNKNOWN
Author-email: UNKNOWN
License: GPL
Platform: UNKNOWN
Classifier: Framework :: Plone
Classifier: Programming Language :: Python
Classifier: Topic :: Software Development :: Libraries :: Python Modules
